README.md
setup.py
EMLM/EMLM.py
EMLM/__init__.py
EMLM.egg-info/PKG-INFO
EMLM.egg-info/SOURCES.txt
EMLM.egg-info/dependency_links.txt
EMLM.egg-info/requires.txt
EMLM.egg-info/top_level.txt