Metadata-Version: 2.1
Name: EMLM
Version: 0.1
Summary: A package for Bayesian linear regression with mixture models
Home-page: https://github.com/yourusername/EMLM
Author: Your Name
Author-email: sidhuser2690@gmail.com
License: MIT
Platform: UNKNOWN
Classifier: Development Status :: 3 - Alpha
Classifier: Intended Audience :: Developers
Classifier: License :: OSI Approved :: MIT License
Classifier: Programming Language :: Python :: 3
Classifier: Programming Language :: Python :: 3.6
Classifier: Programming Language :: Python :: 3.7
Classifier: Programming Language :: Python :: 3.8
